mkstorm/__init__.py
mkstorm/displayer.py
mkstorm/controller/__init__.py
mkstorm/controller/factor_analysis.py
mkstorm/controller/transformer.py
mkstorm/lib/__init__.py
mkstorm/lib/file.py
mkstorm/lib/message.py
mkstorm/load/__init__.py
mkstorm/load/csv.py
mkstorm/view/__init__.py
mkstorm/view/plt.py
storm/__init__.py
storm/displayer.py
storm/controller/__init__.py
storm/controller/factor_analysis.py
storm/controller/transformer.py
storm/load/__init__.py
storm/load/csv.py
storm/view/__init__.py
storm/view/plt.py
mkstorm-0.0.14.dist-info/METADATA
mkstorm-0.0.14.dist-info/WHEEL
mkstorm-0.0.14.dist-info/entry_points.txt
mkstorm-0.0.14.dist-info/top_level.txt
mkstorm-0.0.14.dist-info/RECORD
