Metadata-Version: 2.1
Name: mkstorm
Version: 0.0.14
Summary: Package Dependency: Validates package requirements
Home-page: https://github.com/Shochan024/mkstorm
Author: shochan
Author-email: jadetech0024@gmail.com
Maintainer: kinpira
Maintainer-email: jadetech0024@gmail.com
License: MIT
Platform: UNKNOWN
Classifier: Programming Language :: Python :: 3
Classifier: Programming Language :: Python :: 3.3
Classifier: Programming Language :: Python :: 3.4
Classifier: License :: OSI Approved :: MIT License
Requires-Dist: colorama
